README.md
setup.py
staroid/__init__.py
staroid/cluster.py
staroid/commit.py
staroid/namespace.py
staroid/staroid.py
staroid.egg-info/PKG-INFO
staroid.egg-info/SOURCES.txt
staroid.egg-info/dependency_links.txt
staroid.egg-info/requires.txt
staroid.egg-info/top_level.txt
tests/__init__.py
tests/test_cluster.py
tests/test_commit.py
tests/test_namespace.py
tests/test_staroid.py