Metadata-Version: 2.1
Name: staroid
Version: 0.0.6
Summary: Python client library for Staroid cloud platform
Home-page: https://github.com/staroids/staroid-python
Author: Staroid
Author-email: support@staroid.com
License: MIT
Platform: UNKNOWN
Classifier: Development Status :: 5 - Production/Stable
Classifier: Intended Audience :: Developers
Classifier: Topic :: Software Development :: Libraries
Classifier: Programming Language :: Python :: 3.6
Classifier: Programming Language :: Python :: 3.7
Classifier: Programming Language :: Python :: 3.8
Classifier: License :: OSI Approved :: MIT License
Classifier: Operating System :: OS Independent
Requires-Python: >=3.6
